easyedit2/__init__.py
easyedit2-0.0.1.dev0.dist-info/METADATA
easyedit2-0.0.1.dev0.dist-info/WHEEL
easyedit2-0.0.1.dev0.dist-info/top_level.txt
easyedit2-0.0.1.dev0.dist-info/RECORD
