Metadata-Version: 2.1
Name: easyedit2
Version: 0.0.1.dev0
Summary: An Easy-to-use Steering Framework for Editing Large Language Models
Home-page: https://github.com/zjunlp/EasyEdit
Author: zjuwen
Author-email: 519297864@qq.com
Classifier: Programming Language :: Python :: 3
Classifier: License :: OSI Approved :: MIT License
Requires-Python: >=3.9
